{
	"id": "1",
	"name": "Cinéarts @ Santana Row",
	"address": {"street": "3088 Olsen Drive", "city": "San Jose", "zip":95128, "state": "CA"},
	"phone": "408 554-700",
	"amenities": ["Wheelchair Accessible", "Listening Devices", "Café", "Stadium Seating", "Digital Projection" ], 
	"location": {
		"type": "Point",
		"coordinates": [
			37.318783,
			-121.949142
		]
	}
},
{
	"id": "2",
	"name": "Cinelux Almaden Cinema",
	"address": {"street": "2306 Almaden Road", "city": "San Jose", "zip":95125, "state": "CA"},
	"phone": "408 265-7373",
	"amenities": ["Wheelchair Accessible", "Listening Devices", "Party Room", "Stadium Seating", "Digital Projection" ],
	"location": {
		"type": "Point",
		"coordinates": [
			37.318783,
			-121.949142
		]
	}
},
{
	"id": "3",
	"name": "AMC Eastridege",
	"address": {"street": "2190 Eastridge Loop", "city": "San Jose", "state": "CA", "zip": 95122},
	"phone": "408 274-2274",
	"amenities": ["IMAX", "Digital Projection" ],
	"location": {
		"type": "Point",
		"coordinates": [
			37.318783,
			-121.949142
		]
	},
},
{
	"id": "4",
	"name": "Century 20 Oakridge and XD",
	"address": {"street": "925 Blossom Hill Rd", "city": "San Jose", "zip":95123, "state": "CA"},
	"phone": "408 225-7340",
	"amenities": ["Wheelchair Accessible", "Listening Devices", "Café", ""Stadium Seating", "Game Room" ],
	"location": {
		"type": "Point",
		"coordinates": [
			37.318783,
			-121.949142
		]
	},
},
{
	"id": "5",
	"name": "Century 20 Great Mall and XD",
	"address": {"street": "1010 Great Mall Drive", "city": "Milpitas", "zip":95035, "state": "CA"},
	"phone": "408 942-7441",
	"amenities": ["Wheelchair Accessible", "Café", "Stadium Seating", "Game Room" ],
	"location": {
		"type": "Point",
		"coordinates": [
			37.318783,
			-121.949142
		]
	},
},
{
	"id": "6",
	"name": "Cinelux Plaza Theatre",
	"address": {"street": "2501 S. Winchester Blvd", "city": "Campbell", "zip":95008, "state": "CA"},
	"phone": "408 378-2425",
	"amenities": ["Wheelchair Accessible", "Listening Devices", "Game Room", "Stadium Seating", "Digital Projection" ],
	"location": {
		"type": "Point",
		"coordinates": [
			37.318783,
			-121.949142
		]
	}
},
{
	"id": "7",
	"name": "AMC Mercado",
	"address": {"street": "3111 Mission College Blvd", "city": "Santa Clara", "zip":95054, "state": "CA"},
	"phone": "408 919-0282",
	"amenities": ["IMAX", "Digital Projection" ],
	"location": {
		"type": "Point",
		"coordinates": [
			37.318783,
			-121.949142
		]
	}
},
{
	"id": "8",
	"name": "AMC Cupertino Square",,
	"address": {"street": "10123 N. Wolfe Road", "city": "Cupertino", "zip": 95014, "state": "CA"},
	"phone": "408 554-700",
	"amenities": ["IMAX", "Digital Projection" ],
	"location": {
		"type": "Point",
		"coordinates": [
			37.318783,
			-121.949142
		]
	}
},
{
	"id": "8",
	"name": "Camera 7",
	"address": {"street": "1875 S. Bascom Ave", "city": "Campbell", "zip":95008, "state": "CA"},
	"phone": "408 559-6900",
	"location": {
		"type": "Point",
		"coordinates": [
			37.318783,
			-121.949142
		]
	}
},
{
	"id": "10",
	"name": "Bluelight Cinemas",
	"address": {"street": "21275 Stevens Creek Blvd", "city": "Cupertino", "zip":95014, "state": "CA"},,
	"phone": "408 554-700",
	"location": {
		"type": "Point",
		"coordinates": [
			37.318783,
			-121.949142
		]
	}
}